{
    "date": "Wed Jan 18 23:21:47 CET 2017\n\nremoved classes \n\nzipped \n\ncopied zip \n\n", 
    "gens": "63", 
    "node": "graphene-17.nancy.grid5000.fr", 
    "operations": [
        {
            "buggyStatement": "delta = 0.5 * dx", 
            "generation": 79, 
            "ingredients": null, 
            "patch": "y1 = f.value(x1)", 
            "patchLocation": {
                "className": "org.apache.commons.math.analysis.solvers.BrentSolver", 
                "line": 282, 
                "lineSusp": "0"
            }, 
            "patchvalidation": {
                "evalresult": "false", 
                "evaltcall": "36", 
                "evaltcfailing": "5", 
                "fvalresult": "true", 
                "fvaltcall": "1", 
                "fvaltcfailing": "0", 
                "mvalresult": "false", 
                "mvaltcall": "2106", 
                "mvaltcfailing": "3"
            }, 
            "scope": "LOCAL", 
            "time": "335", 
            "type": "ReplaceOp", 
            "variant": 158
        }, 
        {
            "buggyStatement": "delta = 0.5 * dx", 
            "generation": 84, 
            "ingredients": null, 
            "patch": "remove", 
            "patchLocation": {
                "className": "org.apache.commons.math.analysis.solvers.BrentSolver", 
                "line": 282, 
                "lineSusp": "0"
            }, 
            "patchvalidation": {
                "evalresult": "false", 
                "evaltcall": "36", 
                "evaltcfailing": "5", 
                "fvalresult": "true", 
                "fvaltcall": "1", 
                "fvaltcfailing": "0", 
                "mvalresult": "false", 
                "mvaltcall": "2106", 
                "mvaltcfailing": "3"
            }, 
            "scope": "-", 
            "time": "411", 
            "type": "RemoveOp", 
            "variant": 168
        }, 
        {
            "buggyStatement": "oldDelta = delta", 
            "generation": 85, 
            "ingredients": null, 
            "patch": "delta = (x0 - x1) / (1 - (y0 / y1))", 
            "patchLocation": {
                "className": "org.apache.commons.math.analysis.solvers.BrentSolver", 
                "line": 283, 
                "lineSusp": "0"
            }, 
            "patchvalidation": {
                "evalresult": "false", 
                "evaltcall": "36", 
                "evaltcfailing": "6", 
                "fvalresult": "true", 
                "fvaltcall": "1", 
                "fvaltcfailing": "0", 
                "mvalresult": "false", 
                "mvaltcall": "2106", 
                "mvaltcfailing": "2"
            }, 
            "scope": "PACKAGE", 
            "time": "485", 
            "type": "InsertBeforeOp", 
            "variant": 170
        }, 
        {
            "buggyStatement": "solver.setAbsoluteAccuracy(convergence)", 
            "generation": 90, 
            "ingredients": null, 
            "patch": "remove", 
            "patchLocation": {
                "className": "org.apache.commons.math.ode.events.EventState", 
                "line": 216, 
                "lineSusp": "0"
            }, 
            "patchvalidation": {
                "evalresult": "true", 
                "evaltcall": "22", 
                "evaltcfailing": "0", 
                "fvalresult": "true", 
                "fvaltcall": "1", 
                "fvaltcfailing": "0", 
                "mvalresult": "false", 
                "mvaltcall": "2106", 
                "mvaltcfailing": "10"
            }, 
            "scope": "-", 
            "time": "607", 
            "type": "RemoveOp", 
            "variant": 180
        }, 
        {
            "buggyStatement": "oldDelta = delta", 
            "generation": 125, 
            "ingredients": null, 
            "patch": "delta = x1 - x0", 
            "patchLocation": {
                "className": "org.apache.commons.math.analysis.solvers.BrentSolver", 
                "line": 283, 
                "lineSusp": "0"
            }, 
            "patchvalidation": {
                "evalresult": "false", 
                "evaltcall": "36", 
                "evaltcfailing": "5", 
                "fvalresult": "true", 
                "fvaltcall": "1", 
                "fvaltcfailing": "0", 
                "mvalresult": "false", 
                "mvaltcall": "2106", 
                "mvaltcfailing": "3"
            }, 
            "scope": "LOCAL", 
            "time": "705", 
            "type": "InsertAfterOp", 
            "variant": 250
        }, 
        {
            "buggyStatement": "delta = 0.5 * dx", 
            "generation": 227, 
            "ingredients": null, 
            "patch": "remove", 
            "patchLocation": {
                "className": "org.apache.commons.math.analysis.solvers.BrentSolver", 
                "line": 282, 
                "lineSusp": "0"
            }, 
            "patchvalidation": {
                "evalresult": "false", 
                "evaltcall": "36", 
                "evaltcfailing": "5", 
                "fvalresult": "true", 
                "fvaltcall": "1", 
                "fvaltcfailing": "0", 
                "mvalresult": "false", 
                "mvaltcall": "2106", 
                "mvaltcfailing": "3"
            }, 
            "scope": "-", 
            "time": "855", 
            "type": "RemoveOp", 
            "variant": 454
        }, 
        {
            "buggyStatement": "absoluteAccuracy = accuracy", 
            "generation": 255, 
            "ingredients": null, 
            "patch": "org.apache.commons.math.ConvergingAlgorithmImpl.this.defaultAbsoluteAccuracy = defaultAbsoluteAccuracy", 
            "patchLocation": {
                "className": "org.apache.commons.math.ConvergingAlgorithmImpl", 
                "line": 78, 
                "lineSusp": "0"
            }, 
            "patchvalidation": {
                "evalresult": "false", 
                "evaltcall": "18", 
                "evaltcfailing": "3", 
                "fvalresult": "true", 
                "fvaltcall": "1", 
                "fvaltcfailing": "0", 
                "mvalresult": "false", 
                "mvaltcall": "2106", 
                "mvaltcfailing": "10"
            }, 
            "scope": "LOCAL", 
            "time": "990", 
            "type": "ReplaceOp", 
            "variant": 510
        }, 
        {
            "buggyStatement": "delta = 0.5 * dx", 
            "generation": 337, 
            "ingredients": null, 
            "patch": "oldDelta = delta", 
            "patchLocation": {
                "className": "org.apache.commons.math.analysis.solvers.BrentSolver", 
                "line": 282, 
                "lineSusp": "0"
            }, 
            "patchvalidation": {
                "evalresult": "false", 
                "evaltcall": "36", 
                "evaltcfailing": "5", 
                "fvalresult": "true", 
                "fvaltcall": "1", 
                "fvaltcfailing": "0", 
                "mvalresult": "false", 
                "mvaltcall": "2106", 
                "mvaltcfailing": "3"
            }, 
            "scope": "LOCAL", 
            "time": "1132", 
            "type": "ReplaceOp", 
            "variant": 674
        }, 
        {
            "buggyStatement": "absoluteAccuracy = accuracy", 
            "generation": 338, 
            "ingredients": null, 
            "patch": "org.apache.commons.math.ConvergingAlgorithmImpl.this.defaultRelativeAccuracy = 1.0E-14", 
            "patchLocation": {
                "className": "org.apache.commons.math.ConvergingAlgorithmImpl", 
                "line": 78, 
                "lineSusp": "0"
            }, 
            "patchvalidation": {
                "evalresult": "false", 
                "evaltcall": "18", 
                "evaltcfailing": "3", 
                "fvalresult": "true", 
                "fvaltcall": "1", 
                "fvaltcfailing": "0", 
                "mvalresult": "false", 
                "mvaltcall": "2106", 
                "mvaltcfailing": "10"
            }, 
            "scope": "LOCAL", 
            "time": "1207", 
            "type": "ReplaceOp", 
            "variant": 676
        }, 
        {
            "buggyStatement": "t0 = t", 
            "generation": 340, 
            "ingredients": null, 
            "patch": "g0Positive = true", 
            "patchLocation": {
                "className": "org.apache.commons.math.ode.events.EventState", 
                "line": 285, 
                "lineSusp": "0"
            }, 
            "patchvalidation": {
                "evalresult": "true", 
                "evaltcall": "22", 
                "evaltcfailing": "0", 
                "fvalresult": "true", 
                "fvaltcall": "1", 
                "fvaltcfailing": "0", 
                "mvalresult": "false", 
                "mvaltcall": "2106", 
                "mvaltcfailing": "11"
            }, 
            "scope": "LOCAL", 
            "time": "1280", 
            "type": "ReplaceOp", 
            "variant": 680
        }, 
        {
            "buggyStatement": "delta = 0.5 * dx", 
            "generation": 438, 
            "ingredients": null, 
            "patch": "delta = x1 - x0", 
            "patchLocation": {
                "className": "org.apache.commons.math.analysis.solvers.BrentSolver", 
                "line": 282, 
                "lineSusp": "0"
            }, 
            "patchvalidation": {
                "evalresult": "false", 
                "evaltcall": "36", 
                "evaltcfailing": "5", 
                "fvalresult": "true", 
                "fvaltcall": "1", 
                "fvaltcfailing": "0", 
                "mvalresult": "false", 
                "mvaltcall": "2106", 
                "mvaltcfailing": "2"
            }, 
            "scope": "LOCAL", 
            "time": "1437", 
            "type": "ReplaceOp", 
            "variant": 876
        }, 
        {
            "buggyStatement": "absoluteAccuracy = accuracy", 
            "generation": 446, 
            "ingredients": null, 
            "patch": "absoluteAccuracy = defaultAbsoluteAccuracy", 
            "patchLocation": {
                "className": "org.apache.commons.math.ConvergingAlgorithmImpl", 
                "line": 78, 
                "lineSusp": "0"
            }, 
            "patchvalidation": {
                "evalresult": "false", 
                "evaltcall": "18", 
                "evaltcfailing": "3", 
                "fvalresult": "true", 
                "fvaltcall": "1", 
                "fvaltcfailing": "0", 
                "mvalresult": "false", 
                "mvaltcall": "2106", 
                "mvaltcfailing": "10"
            }, 
            "scope": "LOCAL", 
            "time": "1516", 
            "type": "ReplaceOp", 
            "variant": 892
        }, 
        {
            "buggyStatement": "delta = 0.5 * dx", 
            "generation": 454, 
            "ingredients": null, 
            "patch": "remove", 
            "patchLocation": {
                "className": "org.apache.commons.math.analysis.solvers.BrentSolver", 
                "line": 282, 
                "lineSusp": "0"
            }, 
            "patchvalidation": {
                "evalresult": "false", 
                "evaltcall": "36", 
                "evaltcfailing": "5", 
                "fvalresult": "true", 
                "fvaltcall": "1", 
                "fvaltcfailing": "0", 
                "mvalresult": "false", 
                "mvaltcall": "2106", 
                "mvaltcfailing": "3"
            }, 
            "scope": "-", 
            "time": "1595", 
            "type": "RemoveOp", 
            "variant": 908
        }, 
        {
            "buggyStatement": "solver.setAbsoluteAccuracy(convergence)", 
            "generation": 483, 
            "ingredients": null, 
            "patch": "interpolator.setInterpolatedTime(tb)", 
            "patchLocation": {
                "className": "org.apache.commons.math.ode.events.EventState", 
                "line": 216, 
                "lineSusp": "0"
            }, 
            "patchvalidation": {
                "evalresult": "true", 
                "evaltcall": "22", 
                "evaltcfailing": "0", 
                "fvalresult": "true", 
                "fvaltcall": "1", 
                "fvaltcfailing": "0", 
                "mvalresult": "false", 
                "mvaltcall": "2106", 
                "mvaltcfailing": "9"
            }, 
            "scope": "LOCAL", 
            "time": "1712", 
            "type": "ReplaceOp", 
            "variant": 966
        }, 
        {
            "buggyStatement": "absoluteAccuracy = accuracy", 
            "generation": 520, 
            "ingredients": null, 
            "patch": "org.apache.commons.math.ConvergingAlgorithmImpl.this.iterationCount = 0", 
            "patchLocation": {
                "className": "org.apache.commons.math.ConvergingAlgorithmImpl", 
                "line": 78, 
                "lineSusp": "0"
            }, 
            "patchvalidation": {
                "evalresult": "false", 
                "evaltcall": "18", 
                "evaltcfailing": "3", 
                "fvalresult": "true", 
                "fvaltcall": "1", 
                "fvaltcfailing": "0", 
                "mvalresult": "false", 
                "mvaltcall": "2106", 
                "mvaltcfailing": "10"
            }, 
            "scope": "LOCAL", 
            "time": "1826", 
            "type": "ReplaceOp", 
            "variant": 1040
        }, 
        {
            "buggyStatement": "solver.setAbsoluteAccuracy(convergence)", 
            "generation": 537, 
            "ingredients": null, 
            "patch": "solver.setMaximalIterationCount(maxIterationCount)", 
            "patchLocation": {
                "className": "org.apache.commons.math.ode.events.EventState", 
                "line": 216, 
                "lineSusp": "0"
            }, 
            "patchvalidation": {
                "evalresult": "true", 
                "evaltcall": "22", 
                "evaltcfailing": "0", 
                "fvalresult": "true", 
                "fvaltcall": "1", 
                "fvaltcfailing": "0", 
                "mvalresult": "false", 
                "mvaltcall": "2106", 
                "mvaltcfailing": "9"
            }, 
            "scope": "LOCAL", 
            "time": "1909", 
            "type": "ReplaceOp", 
            "variant": 1074
        }, 
        {
            "buggyStatement": "final double t1 = interpolator.getCurrentTime()", 
            "generation": 591, 
            "ingredients": null, 
            "patch": "final double t0 = interpolator.getPreviousTime()", 
            "patchLocation": {
                "className": "org.apache.commons.math.ode.events.EventState", 
                "line": 173, 
                "lineSusp": "0"
            }, 
            "patchvalidation": {
                "evalresult": "true", 
                "evaltcall": "22", 
                "evaltcfailing": "0", 
                "fvalresult": "true", 
                "fvaltcall": "1", 
                "fvaltcfailing": "0", 
                "mvalresult": "true", 
                "mvaltcall": "2106", 
                "mvaltcfailing": "0"
            }, 
            "scope": "PACKAGE", 
            "time": "2033", 
            "type": "InsertBeforeOp", 
            "variant": 1182
        }, 
        {
            "buggyStatement": "absoluteAccuracy = accuracy", 
            "generation": 633, 
            "ingredients": null, 
            "patch": "remove", 
            "patchLocation": {
                "className": "org.apache.commons.math.ConvergingAlgorithmImpl", 
                "line": 78, 
                "lineSusp": "0"
            }, 
            "patchvalidation": {
                "evalresult": "false", 
                "evaltcall": "18", 
                "evaltcfailing": "3", 
                "fvalresult": "true", 
                "fvaltcall": "1", 
                "fvaltcfailing": "0", 
                "mvalresult": "false", 
                "mvaltcall": "2106", 
                "mvaltcfailing": "10"
            }, 
            "scope": "-", 
            "time": "2142", 
            "type": "RemoveOp", 
            "variant": 1266
        }, 
        {
            "buggyStatement": "solver.setAbsoluteAccuracy(convergence)", 
            "generation": 654, 
            "ingredients": null, 
            "patch": "interpolator.setInterpolatedTime(t0)", 
            "patchLocation": {
                "className": "org.apache.commons.math.ode.events.EventState", 
                "line": 216, 
                "lineSusp": "0"
            }, 
            "patchvalidation": {
                "evalresult": "true", 
                "evaltcall": "22", 
                "evaltcfailing": "0", 
                "fvalresult": "true", 
                "fvaltcall": "1", 
                "fvaltcfailing": "0", 
                "mvalresult": "false", 
                "mvaltcall": "2106", 
                "mvaltcfailing": "9"
            }, 
            "scope": "PACKAGE", 
            "time": "2229", 
            "type": "ReplaceOp", 
            "variant": 1308
        }, 
        {
            "buggyStatement": "absoluteAccuracy = accuracy", 
            "generation": 691, 
            "ingredients": null, 
            "patch": "remove", 
            "patchLocation": {
                "className": "org.apache.commons.math.ConvergingAlgorithmImpl", 
                "line": 78, 
                "lineSusp": "0"
            }, 
            "patchvalidation": {
                "evalresult": "false", 
                "evaltcall": "18", 
                "evaltcfailing": "3", 
                "fvalresult": "true", 
                "fvaltcall": "1", 
                "fvaltcfailing": "0", 
                "mvalresult": "false", 
                "mvaltcall": "2106", 
                "mvaltcfailing": "10"
            }, 
            "scope": "-", 
            "time": "2340", 
            "type": "RemoveOp", 
            "variant": 1382
        }, 
        {
            "buggyStatement": "t0 = t", 
            "generation": 706, 
            "ingredients": null, 
            "patch": "remove", 
            "patchLocation": {
                "className": "org.apache.commons.math.ode.events.EventState", 
                "line": 285, 
                "lineSusp": "0"
            }, 
            "patchvalidation": {
                "evalresult": "true", 
                "evaltcall": "22", 
                "evaltcfailing": "0", 
                "fvalresult": "true", 
                "fvaltcall": "1", 
                "fvaltcfailing": "0", 
                "mvalresult": "false", 
                "mvaltcall": "2106", 
                "mvaltcfailing": "11"
            }, 
            "scope": "-", 
            "time": "2425", 
            "type": "RemoveOp", 
            "variant": 1412
        }, 
        {
            "buggyStatement": "delta = 0.5 * dx", 
            "generation": 723, 
            "ingredients": null, 
            "patch": "x1 = x1 - (0.5 * tolerance)", 
            "patchLocation": {
                "className": "org.apache.commons.math.analysis.solvers.BrentSolver", 
                "line": 282, 
                "lineSusp": "0"
            }, 
            "patchvalidation": {
                "evalresult": "false", 
                "evaltcall": "36", 
                "evaltcfailing": "5", 
                "fvalresult": "true", 
                "fvaltcall": "1", 
                "fvaltcfailing": "0", 
                "mvalresult": "false", 
                "mvaltcall": "2106", 
                "mvaltcfailing": "2"
            }, 
            "scope": "LOCAL", 
            "time": "2517", 
            "type": "ReplaceOp", 
            "variant": 1446
        }, 
        {
            "buggyStatement": "delta = 0.5 * dx", 
            "generation": 745, 
            "ingredients": null, 
            "patch": "y2 = y0", 
            "patchLocation": {
                "className": "org.apache.commons.math.analysis.solvers.BrentSolver", 
                "line": 282, 
                "lineSusp": "0"
            }, 
            "patchvalidation": {
                "evalresult": "false", 
                "evaltcall": "36", 
                "evaltcfailing": "5", 
                "fvalresult": "true", 
                "fvaltcall": "1", 
                "fvaltcfailing": "0", 
                "mvalresult": "false", 
                "mvaltcall": "2106", 
                "mvaltcfailing": "5"
            }, 
            "scope": "LOCAL", 
            "time": "2603", 
            "type": "ReplaceOp", 
            "variant": 1490
        }, 
        {
            "buggyStatement": "delta = 0.5 * dx", 
            "generation": 892, 
            "ingredients": null, 
            "patch": "remove", 
            "patchLocation": {
                "className": "org.apache.commons.math.analysis.solvers.BrentSolver", 
                "line": 282, 
                "lineSusp": "0"
            }, 
            "patchvalidation": {
                "evalresult": "false", 
                "evaltcall": "36", 
                "evaltcfailing": "5", 
                "fvalresult": "true", 
                "fvaltcall": "1", 
                "fvaltcfailing": "0", 
                "mvalresult": "false", 
                "mvaltcall": "2106", 
                "mvaltcfailing": "3"
            }, 
            "scope": "-", 
            "time": "2827", 
            "type": "RemoveOp", 
            "variant": 1784
        }, 
        {
            "buggyStatement": "absoluteAccuracy = accuracy", 
            "generation": 920, 
            "ingredients": null, 
            "patch": "org.apache.commons.math.ConvergingAlgorithmImpl.this.defaultMaximalIterationCount = defaultMaximalIterationCount", 
            "patchLocation": {
                "className": "org.apache.commons.math.ConvergingAlgorithmImpl", 
                "line": 78, 
                "lineSusp": "0"
            }, 
            "patchvalidation": {
                "evalresult": "false", 
                "evaltcall": "18", 
                "evaltcfailing": "3", 
                "fvalresult": "true", 
                "fvaltcall": "1", 
                "fvaltcfailing": "0", 
                "mvalresult": "false", 
                "mvaltcall": "2106", 
                "mvaltcfailing": "10"
            }, 
            "scope": "LOCAL", 
            "time": "2921", 
            "type": "ReplaceOp", 
            "variant": 1840
        }, 
        {
            "buggyStatement": "absoluteAccuracy = accuracy", 
            "generation": 937, 
            "ingredients": null, 
            "patch": "remove", 
            "patchLocation": {
                "className": "org.apache.commons.math.ConvergingAlgorithmImpl", 
                "line": 78, 
                "lineSusp": "0"
            }, 
            "patchvalidation": {
                "evalresult": "false", 
                "evaltcall": "18", 
                "evaltcfailing": "3", 
                "fvalresult": "true", 
                "fvaltcall": "1", 
                "fvaltcfailing": "0", 
                "mvalresult": "false", 
                "mvaltcall": "2106", 
                "mvaltcfailing": "10"
            }, 
            "scope": "-", 
            "time": "3012", 
            "type": "RemoveOp", 
            "variant": 1874
        }, 
        {
            "buggyStatement": "absoluteAccuracy = accuracy", 
            "generation": 988, 
            "ingredients": null, 
            "patch": "maximalIterationCount = defaultMaximalIterationCount", 
            "patchLocation": {
                "className": "org.apache.commons.math.ConvergingAlgorithmImpl", 
                "line": 78, 
                "lineSusp": "0"
            }, 
            "patchvalidation": {
                "evalresult": "false", 
                "evaltcall": "18", 
                "evaltcfailing": "3", 
                "fvalresult": "true", 
                "fvaltcall": "1", 
                "fvaltcfailing": "0", 
                "mvalresult": "false", 
                "mvaltcall": "2106", 
                "mvaltcfailing": "10"
            }, 
            "scope": "LOCAL", 
            "time": "3138", 
            "type": "ReplaceOp", 
            "variant": 1976
        }, 
        {
            "buggyStatement": "p1 = ((r1 - 1.0) * (r2 - 1.0)) * (r3 - 1.0)", 
            "generation": 1025, 
            "ingredients": null, 
            "patch": "p1 = 1.0 - r3", 
            "patchLocation": {
                "className": "org.apache.commons.math.analysis.solvers.BrentSolver", 
                "line": 270, 
                "lineSusp": "0"
            }, 
            "patchvalidation": {
                "evalresult": "false", 
                "evaltcall": "36", 
                "evaltcfailing": "7", 
                "fvalresult": "true", 
                "fvaltcall": "1", 
                "fvaltcfailing": "0", 
                "mvalresult": "false", 
                "mvaltcall": "2106", 
                "mvaltcfailing": "4"
            }, 
            "scope": "LOCAL", 
            "time": "3242", 
            "type": "ReplaceOp", 
            "variant": 2050
        }, 
        {
            "buggyStatement": "delta = 0.5 * dx", 
            "generation": 1050, 
            "ingredients": null, 
            "patch": "remove", 
            "patchLocation": {
                "className": "org.apache.commons.math.analysis.solvers.BrentSolver", 
                "line": 282, 
                "lineSusp": "0"
            }, 
            "patchvalidation": {
                "evalresult": "false", 
                "evaltcall": "36", 
                "evaltcfailing": "5", 
                "fvalresult": "true", 
                "fvaltcall": "1", 
                "fvaltcfailing": "0", 
                "mvalresult": "false", 
                "mvaltcall": "2106", 
                "mvaltcfailing": "3"
            }, 
            "scope": "-", 
            "time": "3339", 
            "type": "RemoveOp", 
            "variant": 2100
        }, 
        {
            "buggyStatement": "absoluteAccuracy = accuracy", 
            "generation": 1085, 
            "ingredients": null, 
            "patch": "remove", 
            "patchLocation": {
                "className": "org.apache.commons.math.ConvergingAlgorithmImpl", 
                "line": 78, 
                "lineSusp": "0"
            }, 
            "patchvalidation": {
                "evalresult": "false", 
                "evaltcall": "18", 
                "evaltcfailing": "3", 
                "fvalresult": "true", 
                "fvaltcall": "1", 
                "fvaltcfailing": "0", 
                "mvalresult": "false", 
                "mvaltcall": "2106", 
                "mvaltcfailing": "10"
            }, 
            "scope": "-", 
            "time": "3451", 
            "type": "RemoveOp", 
            "variant": 2170
        }, 
        {
            "buggyStatement": "oldDelta = delta", 
            "generation": 1104, 
            "ingredients": null, 
            "patch": "delta = x1 - x0", 
            "patchLocation": {
                "className": "org.apache.commons.math.analysis.solvers.BrentSolver", 
                "line": 283, 
                "lineSusp": "0"
            }, 
            "patchvalidation": {
                "evalresult": "false", 
                "evaltcall": "36", 
                "evaltcfailing": "5", 
                "fvalresult": "true", 
                "fvaltcall": "1", 
                "fvaltcfailing": "0", 
                "mvalresult": "false", 
                "mvaltcall": "2106", 
                "mvaltcfailing": "2"
            }, 
            "scope": "LOCAL", 
            "time": "3534", 
            "type": "InsertBeforeOp", 
            "variant": 2208
        }, 
        {
            "buggyStatement": "absoluteAccuracy = accuracy", 
            "generation": 1112, 
            "ingredients": null, 
            "patch": "remove", 
            "patchLocation": {
                "className": "org.apache.commons.math.ConvergingAlgorithmImpl", 
                "line": 78, 
                "lineSusp": "0"
            }, 
            "patchvalidation": {
                "evalresult": "false", 
                "evaltcall": "18", 
                "evaltcfailing": "3", 
                "fvalresult": "true", 
                "fvaltcall": "1", 
                "fvaltcfailing": "0", 
                "mvalresult": "false", 
                "mvaltcall": "2106", 
                "mvaltcfailing": "10"
            }, 
            "scope": "-", 
            "time": "3612", 
            "type": "RemoveOp", 
            "variant": 2224
        }, 
        {
            "buggyStatement": "delta = 0.5 * dx", 
            "generation": 1122, 
            "ingredients": null, 
            "patch": "x0 = x1", 
            "patchLocation": {
                "className": "org.apache.commons.math.analysis.solvers.BrentSolver", 
                "line": 282, 
                "lineSusp": "0"
            }, 
            "patchvalidation": {
                "evalresult": "false", 
                "evaltcall": "36", 
                "evaltcfailing": "5", 
                "fvalresult": "true", 
                "fvaltcall": "1", 
                "fvaltcfailing": "0", 
                "mvalresult": "false", 
                "mvaltcall": "2106", 
                "mvaltcfailing": "3"
            }, 
            "scope": "LOCAL", 
            "time": "3690", 
            "type": "ReplaceOp", 
            "variant": 2244
        }, 
        {
            "buggyStatement": "solver.setAbsoluteAccuracy(convergence)", 
            "generation": 1140, 
            "ingredients": null, 
            "patch": "remove", 
            "patchLocation": {
                "className": "org.apache.commons.math.ode.events.EventState", 
                "line": 216, 
                "lineSusp": "0"
            }, 
            "patchvalidation": {
                "evalresult": "true", 
                "evaltcall": "22", 
                "evaltcfailing": "0", 
                "fvalresult": "true", 
                "fvaltcall": "1", 
                "fvaltcfailing": "0", 
                "mvalresult": "false", 
                "mvaltcall": "2106", 
                "mvaltcfailing": "9"
            }, 
            "scope": "-", 
            "time": "3787", 
            "type": "RemoveOp", 
            "variant": 2280
        }, 
        {
            "buggyStatement": "solver.setAbsoluteAccuracy(convergence)", 
            "generation": 1148, 
            "ingredients": null, 
            "patch": "remove", 
            "patchLocation": {
                "className": "org.apache.commons.math.ode.events.EventState", 
                "line": 216, 
                "lineSusp": "0"
            }, 
            "patchvalidation": {
                "evalresult": "true", 
                "evaltcall": "22", 
                "evaltcfailing": "0", 
                "fvalresult": "true", 
                "fvaltcall": "1", 
                "fvaltcfailing": "0", 
                "mvalresult": "false", 
                "mvaltcall": "2106", 
                "mvaltcfailing": "9"
            }, 
            "scope": "-", 
            "time": "3867", 
            "type": "RemoveOp", 
            "variant": 2296
        }, 
        {
            "buggyStatement": "p = -p", 
            "generation": 1178, 
            "ingredients": null, 
            "patch": "if (dx > 0.0) {\n\tx1 = x1 + (0.5 * tolerance);\n} else {\n\tif (dx <= 0.0) {\n\t\tx1 = x1 - (0.5 * tolerance);\n\t} \n}", 
            "patchLocation": {
                "className": "org.apache.commons.math.analysis.solvers.BrentSolver", 
                "line": 275, 
                "lineSusp": "0"
            }, 
            "patchvalidation": {
                "evalresult": "false", 
                "evaltcall": "36", 
                "evaltcfailing": "4", 
                "fvalresult": "true", 
                "fvaltcall": "1", 
                "fvaltcfailing": "0", 
                "mvalresult": "false", 
                "mvaltcall": "2106", 
                "mvaltcfailing": "11"
            }, 
            "scope": "LOCAL", 
            "time": "3962", 
            "type": "InsertBeforeOp", 
            "variant": 2356
        }, 
        {
            "buggyStatement": "delta = 0.5 * dx", 
            "generation": 1209, 
            "ingredients": null, 
            "patch": "x2 = x0", 
            "patchLocation": {
                "className": "org.apache.commons.math.analysis.solvers.BrentSolver", 
                "line": 282, 
                "lineSusp": "0"
            }, 
            "patchvalidation": {
                "evalresult": "false", 
                "evaltcall": "36", 
                "evaltcfailing": "5", 
                "fvalresult": "true", 
                "fvaltcall": "1", 
                "fvaltcfailing": "0", 
                "mvalresult": "false", 
                "mvaltcall": "2106", 
                "mvaltcfailing": "3"
            }, 
            "scope": "LOCAL", 
            "time": "4063", 
            "type": "ReplaceOp", 
            "variant": 2418
        }, 
        {
            "buggyStatement": "delta = 0.5 * dx", 
            "generation": 1215, 
            "ingredients": null, 
            "patch": "iterationCount = i", 
            "patchLocation": {
                "className": "org.apache.commons.math.analysis.solvers.BrentSolver", 
                "line": 282, 
                "lineSusp": "0"
            }, 
            "patchvalidation": {
                "evalresult": "false", 
                "evaltcall": "36", 
                "evaltcfailing": "5", 
                "fvalresult": "true", 
                "fvaltcall": "1", 
                "fvaltcfailing": "0", 
                "mvalresult": "false", 
                "mvaltcall": "2106", 
                "mvaltcfailing": "3"
            }, 
            "scope": "PACKAGE", 
            "time": "4140", 
            "type": "ReplaceOp", 
            "variant": 2430
        }, 
        {
            "buggyStatement": "solver.setAbsoluteAccuracy(convergence)", 
            "generation": 1222, 
            "ingredients": null, 
            "patch": "remove", 
            "patchLocation": {
                "className": "org.apache.commons.math.ode.events.EventState", 
                "line": 216, 
                "lineSusp": "0"
            }, 
            "patchvalidation": {
                "evalresult": "true", 
                "evaltcall": "22", 
                "evaltcfailing": "0", 
                "fvalresult": "true", 
                "fvaltcall": "1", 
                "fvaltcfailing": "0", 
                "mvalresult": "false", 
                "mvaltcall": "2106", 
                "mvaltcfailing": "9"
            }, 
            "scope": "-", 
            "time": "4218", 
            "type": "RemoveOp", 
            "variant": 2444
        }, 
        {
            "buggyStatement": "for (int i = 0 ; i < n ; ++i) {\n\ttb += h;\n\tinterpolator.setInterpolatedTime(tb);\n\tfinal double gb = handler.g(tb, interpolator.getInterpolatedState());\n\tif ((g0Positive) ^ (gb >= 0)) {\n\t\tincreasing = gb >= ga;\n\t\tfinal org.apache.commons.math.analysis.UnivariateRealFunction f = new org.apache.commons.math.analysis.UnivariateRealFunction() {\n\t\t\tpublic double value(final double t) throws org.apache.commons.math.FunctionEvaluationException {\n\t\t\t\ttry {\n\t\t\t\t\tinterpolator.setInterpolatedTime(t);\n\t\t\t\t\treturn handler.g(t, interpolator.getInterpolatedState());\n\t\t\t\t} catch (org.apache.commons.math.ode.DerivativeException e) {\n\t\t\t\t\tthrow new org.apache.commons.math.FunctionEvaluationException(e , t);\n\t\t\t\t} catch (org.apache.commons.math.ode.events.EventException e) {\n\t\t\t\t\tthrow new org.apache.commons.math.FunctionEvaluationException(e , t);\n\t\t\t\t}\n\t\t\t}\n\t\t};\n\t\tfinal org.apache.commons.math.analysis.solvers.BrentSolver solver = new org.apache.commons.math.analysis.solvers.BrentSolver();\n\t\tsolver.setAbsoluteAccuracy(convergence);\n\t\tsolver.setMaximalIterationCount(maxIterationCount);\n\t\tfinal double root = ta <= tb ? solver.solve(f, ta, tb) : solver.solve(f, tb, ta);\n\t\tif (((java.lang.Math.abs((root - ta))) <= (convergence)) && ((java.lang.Math.abs((root - (previousEventTime)))) <= (convergence))) {\n\t\t\tta = tb;\n\t\t\tga = gb;\n\t\t} else {\n\t\t\tif ((java.lang.Double.isNaN(previousEventTime)) || ((java.lang.Math.abs(((previousEventTime) - root))) > (convergence))) {\n\t\t\t\tpendingEventTime = root;\n\t\t\t\tif ((pendingEvent) && ((java.lang.Math.abs((t1 - (pendingEventTime)))) <= (convergence))) {\n\t\t\t\t\treturn false;\n\t\t\t\t} \n\t\t\t\tpendingEvent = true;\n\t\t\t\treturn true;\n\t\t\t} \n\t\t}\n\t} else {\n\t\tta = tb;\n\t\tga = gb;\n\t}\n}", 
            "generation": 1236, 
            "ingredients": null, 
            "patch": "ta = tb", 
            "patchLocation": {
                "className": "org.apache.commons.math.ode.events.EventState", 
                "line": 180, 
                "lineSusp": "0"
            }, 
            "patchvalidation": {
                "evalresult": "true", 
                "evaltcall": "22", 
                "evaltcfailing": "0", 
                "fvalresult": "true", 
                "fvaltcall": "1", 
                "fvaltcfailing": "0", 
                "mvalresult": "true", 
                "mvaltcall": "2106", 
                "mvaltcfailing": "0"
            }, 
            "scope": "LOCAL", 
            "time": "4296", 
            "type": "InsertBeforeOp", 
            "variant": 2472
        }, 
        {
            "buggyStatement": "delta = 0.5 * dx", 
            "generation": 1254, 
            "ingredients": null, 
            "patch": "remove", 
            "patchLocation": {
                "className": "org.apache.commons.math.analysis.solvers.BrentSolver", 
                "line": 282, 
                "lineSusp": "0"
            }, 
            "patchvalidation": {
                "evalresult": "false", 
                "evaltcall": "36", 
                "evaltcfailing": "5", 
                "fvalresult": "true", 
                "fvaltcall": "1", 
                "fvaltcfailing": "0", 
                "mvalresult": "false", 
                "mvaltcall": "2106", 
                "mvaltcfailing": "3"
            }, 
            "scope": "-", 
            "time": "4382", 
            "type": "RemoveOp", 
            "variant": 2508
        }, 
        {
            "buggyStatement": "delta = 0.5 * dx", 
            "generation": 1353, 
            "ingredients": null, 
            "patch": "remove", 
            "patchLocation": {
                "className": "org.apache.commons.math.analysis.solvers.BrentSolver", 
                "line": 282, 
                "lineSusp": "0"
            }, 
            "patchvalidation": {
                "evalresult": "false", 
                "evaltcall": "36", 
                "evaltcfailing": "5", 
                "fvalresult": "true", 
                "fvaltcall": "1", 
                "fvaltcfailing": "0", 
                "mvalresult": "false", 
                "mvaltcall": "2106", 
                "mvaltcfailing": "3"
            }, 
            "scope": "-", 
            "time": "4536", 
            "type": "RemoveOp", 
            "variant": 2706
        }, 
        {
            "buggyStatement": "delta = 0.5 * dx", 
            "generation": 1404, 
            "ingredients": null, 
            "patch": "delta = (x0 - x1) / (1 - (y0 / y1))", 
            "patchLocation": {
                "className": "org.apache.commons.math.analysis.solvers.BrentSolver", 
                "line": 282, 
                "lineSusp": "0"
            }, 
            "patchvalidation": {
                "evalresult": "false", 
                "evaltcall": "36", 
                "evaltcfailing": "6", 
                "fvalresult": "true", 
                "fvaltcall": "1", 
                "fvaltcfailing": "0", 
                "mvalresult": "false", 
                "mvaltcall": "2106", 
                "mvaltcfailing": "2"
            }, 
            "scope": "PACKAGE", 
            "time": "4652", 
            "type": "InsertAfterOp", 
            "variant": 2808
        }, 
        {
            "buggyStatement": "absoluteAccuracy = accuracy", 
            "generation": 1414, 
            "ingredients": null, 
            "patch": "org.apache.commons.math.ConvergingAlgorithmImpl.this.maximalIterationCount = defaultMaximalIterationCount", 
            "patchLocation": {
                "className": "org.apache.commons.math.ConvergingAlgorithmImpl", 
                "line": 78, 
                "lineSusp": "0"
            }, 
            "patchvalidation": {
                "evalresult": "false", 
                "evaltcall": "18", 
                "evaltcfailing": "3", 
                "fvalresult": "true", 
                "fvaltcall": "1", 
                "fvaltcfailing": "0", 
                "mvalresult": "false", 
                "mvaltcall": "2106", 
                "mvaltcfailing": "10"
            }, 
            "scope": "LOCAL", 
            "time": "4733", 
            "type": "ReplaceOp", 
            "variant": 2828
        }, 
        {
            "buggyStatement": "oldDelta = delta", 
            "generation": 1422, 
            "ingredients": null, 
            "patch": "delta = (x0 - x1) / (1 - (y0 / y1))", 
            "patchLocation": {
                "className": "org.apache.commons.math.analysis.solvers.BrentSolver", 
                "line": 283, 
                "lineSusp": "0"
            }, 
            "patchvalidation": {
                "evalresult": "false", 
                "evaltcall": "36", 
                "evaltcfailing": "6", 
                "fvalresult": "true", 
                "fvaltcall": "1", 
                "fvaltcfailing": "0", 
                "mvalresult": "false", 
                "mvaltcall": "2106", 
                "mvaltcfailing": "2"
            }, 
            "scope": "PACKAGE", 
            "time": "4812", 
            "type": "ReplaceOp", 
            "variant": 2844
        }, 
        {
            "buggyStatement": "t0 = t", 
            "generation": 1443, 
            "ingredients": null, 
            "patch": "remove", 
            "patchLocation": {
                "className": "org.apache.commons.math.ode.events.EventState", 
                "line": 285, 
                "lineSusp": "0"
            }, 
            "patchvalidation": {
                "evalresult": "true", 
                "evaltcall": "22", 
                "evaltcfailing": "0", 
                "fvalresult": "true", 
                "fvaltcall": "1", 
                "fvaltcfailing": "0", 
                "mvalresult": "false", 
                "mvaltcall": "2106", 
                "mvaltcfailing": "11"
            }, 
            "scope": "-", 
            "time": "4905", 
            "type": "RemoveOp", 
            "variant": 2886
        }, 
        {
            "buggyStatement": "solver.setAbsoluteAccuracy(convergence)", 
            "generation": 1463, 
            "ingredients": null, 
            "patch": "remove", 
            "patchLocation": {
                "className": "org.apache.commons.math.ode.events.EventState", 
                "line": 216, 
                "lineSusp": "0"
            }, 
            "patchvalidation": {
                "evalresult": "true", 
                "evaltcall": "22", 
                "evaltcfailing": "0", 
                "fvalresult": "true", 
                "fvaltcall": "1", 
                "fvaltcfailing": "0", 
                "mvalresult": "false", 
                "mvaltcall": "2106", 
                "mvaltcfailing": "10"
            }, 
            "scope": "-", 
            "time": "4995", 
            "type": "RemoveOp", 
            "variant": 2926
        }, 
        {
            "buggyStatement": "p = r3 * (((dx * r1) * (r1 - r2)) - ((x1 - x0) * (r2 - 1.0)))", 
            "generation": 1474, 
            "ingredients": null, 
            "patch": "p = dx * r3", 
            "patchLocation": {
                "className": "org.apache.commons.math.analysis.solvers.BrentSolver", 
                "line": 269, 
                "lineSusp": "0"
            }, 
            "patchvalidation": {
                "evalresult": "false", 
                "evaltcall": "36", 
                "evaltcfailing": "7", 
                "fvalresult": "true", 
                "fvaltcall": "1", 
                "fvaltcfailing": "0", 
                "mvalresult": "false", 
                "mvaltcall": "2106", 
                "mvaltcfailing": "3"
            }, 
            "scope": "LOCAL", 
            "time": "5076", 
            "type": "InsertAfterOp", 
            "variant": 2948
        }, 
        {
            "buggyStatement": "solver.setAbsoluteAccuracy(convergence)", 
            "generation": 1498, 
            "ingredients": null, 
            "patch": "remove", 
            "patchLocation": {
                "className": "org.apache.commons.math.ode.events.EventState", 
                "line": 216, 
                "lineSusp": "0"
            }, 
            "patchvalidation": {
                "evalresult": "true", 
                "evaltcall": "22", 
                "evaltcfailing": "0", 
                "fvalresult": "true", 
                "fvaltcall": "1", 
                "fvaltcfailing": "0", 
                "mvalresult": "false", 
                "mvaltcall": "2106", 
                "mvaltcfailing": "9"
            }, 
            "scope": "-", 
            "time": "5194", 
            "type": "RemoveOp", 
            "variant": 2996
        }, 
        {
            "buggyStatement": "maximalIterationCount = count", 
            "generation": 1604, 
            "ingredients": null, 
            "patch": "absoluteAccuracy = defaultAbsoluteAccuracy", 
            "patchLocation": {
                "className": "org.apache.commons.math.ConvergingAlgorithmImpl", 
                "line": 93, 
                "lineSusp": "0"
            }, 
            "patchvalidation": {
                "evalresult": "false", 
                "evaltcall": "18", 
                "evaltcfailing": "4", 
                "fvalresult": "true", 
                "fvaltcall": "1", 
                "fvaltcfailing": "0", 
                "mvalresult": "false", 
                "mvaltcall": "2106", 
                "mvaltcfailing": "15"
            }, 
            "scope": "LOCAL", 
            "time": "5341", 
            "type": "ReplaceOp", 
            "variant": 3208
        }, 
        {
            "buggyStatement": "delta = 0.5 * dx", 
            "generation": 1615, 
            "ingredients": null, 
            "patch": "p = dx * r3", 
            "patchLocation": {
                "className": "org.apache.commons.math.analysis.solvers.BrentSolver", 
                "line": 282, 
                "lineSusp": "0"
            }, 
            "patchvalidation": {
                "evalresult": "false", 
                "evaltcall": "36", 
                "evaltcfailing": "5", 
                "fvalresult": "true", 
                "fvaltcall": "1", 
                "fvaltcfailing": "0", 
                "mvalresult": "false", 
                "mvaltcall": "2106", 
                "mvaltcfailing": "3"
            }, 
            "scope": "LOCAL", 
            "time": "5422", 
            "type": "ReplaceOp", 
            "variant": 3230
        }, 
        {
            "buggyStatement": "delta = 0.5 * dx", 
            "generation": 1633, 
            "ingredients": null, 
            "patch": "remove", 
            "patchLocation": {
                "className": "org.apache.commons.math.analysis.solvers.BrentSolver", 
                "line": 282, 
                "lineSusp": "0"
            }, 
            "patchvalidation": {
                "evalresult": "false", 
                "evaltcall": "36", 
                "evaltcfailing": "5", 
                "fvalresult": "true", 
                "fvaltcall": "1", 
                "fvaltcfailing": "0", 
                "mvalresult": "false", 
                "mvaltcall": "2106", 
                "mvaltcfailing": "3"
            }, 
            "scope": "-", 
            "time": "5508", 
            "type": "RemoveOp", 
            "variant": 3266
        }, 
        {
            "buggyStatement": "t0 = t", 
            "generation": 1636, 
            "ingredients": null, 
            "patch": "remove", 
            "patchLocation": {
                "className": "org.apache.commons.math.ode.events.EventState", 
                "line": 285, 
                "lineSusp": "0"
            }, 
            "patchvalidation": {
                "evalresult": "true", 
                "evaltcall": "22", 
                "evaltcfailing": "0", 
                "fvalresult": "true", 
                "fvaltcall": "1", 
                "fvaltcfailing": "0", 
                "mvalresult": "false", 
                "mvaltcall": "2106", 
                "mvaltcfailing": "11"
            }, 
            "scope": "-", 
            "time": "5582", 
            "type": "RemoveOp", 
            "variant": 3272
        }, 
        {
            "buggyStatement": "delta = 0.5 * dx", 
            "generation": 1643, 
            "ingredients": null, 
            "patch": "remove", 
            "patchLocation": {
                "className": "org.apache.commons.math.analysis.solvers.BrentSolver", 
                "line": 282, 
                "lineSusp": "0"
            }, 
            "patchvalidation": {
                "evalresult": "false", 
                "evaltcall": "36", 
                "evaltcfailing": "5", 
                "fvalresult": "true", 
                "fvaltcall": "1", 
                "fvaltcfailing": "0", 
                "mvalresult": "false", 
                "mvaltcall": "2106", 
                "mvaltcfailing": "3"
            }, 
            "scope": "-", 
            "time": "5661", 
            "type": "RemoveOp", 
            "variant": 3286
        }, 
        {
            "buggyStatement": "oldDelta = delta", 
            "generation": 1655, 
            "ingredients": null, 
            "patch": "delta = p / p1", 
            "patchLocation": {
                "className": "org.apache.commons.math.analysis.solvers.BrentSolver", 
                "line": 283, 
                "lineSusp": "0"
            }, 
            "patchvalidation": {
                "evalresult": "false", 
                "evaltcall": "36", 
                "evaltcfailing": "5", 
                "fvalresult": "true", 
                "fvaltcall": "1", 
                "fvaltcfailing": "0", 
                "mvalresult": "false", 
                "mvaltcall": "2106", 
                "mvaltcfailing": "2"
            }, 
            "scope": "LOCAL", 
            "time": "5744", 
            "type": "InsertBeforeOp", 
            "variant": 3310
        }, 
        {
            "buggyStatement": "final double h = (t1 - (t0)) / n", 
            "generation": 1671, 
            "ingredients": null, 
            "patch": "final double t0 = interpolator.getPreviousTime()", 
            "patchLocation": {
                "className": "org.apache.commons.math.ode.events.EventState", 
                "line": 175, 
                "lineSusp": "0"
            }, 
            "patchvalidation": {
                "evalresult": "true", 
                "evaltcall": "22", 
                "evaltcfailing": "0", 
                "fvalresult": "true", 
                "fvaltcall": "1", 
                "fvaltcfailing": "0", 
                "mvalresult": "true", 
                "mvaltcall": "2106", 
                "mvaltcfailing": "0"
            }, 
            "scope": "PACKAGE", 
            "time": "5827", 
            "type": "InsertAfterOp", 
            "variant": 3342
        }, 
        {
            "buggyStatement": "oldDelta = delta", 
            "generation": 1674, 
            "ingredients": null, 
            "patch": "delta = x1 - x0", 
            "patchLocation": {
                "className": "org.apache.commons.math.analysis.solvers.BrentSolver", 
                "line": 283, 
                "lineSusp": "0"
            }, 
            "patchvalidation": {
                "evalresult": "false", 
                "evaltcall": "36", 
                "evaltcfailing": "5", 
                "fvalresult": "true", 
                "fvaltcall": "1", 
                "fvaltcfailing": "0", 
                "mvalresult": "false", 
                "mvaltcall": "2106", 
                "mvaltcfailing": "2"
            }, 
            "scope": "LOCAL", 
            "time": "5901", 
            "type": "ReplaceOp", 
            "variant": 3348
        }, 
        {
            "buggyStatement": "t0 = t", 
            "generation": 1690, 
            "ingredients": null, 
            "patch": "remove", 
            "patchLocation": {
                "className": "org.apache.commons.math.ode.events.EventState", 
                "line": 285, 
                "lineSusp": "0"
            }, 
            "patchvalidation": {
                "evalresult": "true", 
                "evaltcall": "22", 
                "evaltcfailing": "0", 
                "fvalresult": "true", 
                "fvaltcall": "1", 
                "fvaltcfailing": "0", 
                "mvalresult": "false", 
                "mvaltcall": "2106", 
                "mvaltcfailing": "11"
            }, 
            "scope": "-", 
            "time": "5988", 
            "type": "RemoveOp", 
            "variant": 3380
        }, 
        {
            "buggyStatement": "delta = 0.5 * dx", 
            "generation": 1725, 
            "ingredients": null, 
            "patch": "y0 = y1", 
            "patchLocation": {
                "className": "org.apache.commons.math.analysis.solvers.BrentSolver", 
                "line": 282, 
                "lineSusp": "0"
            }, 
            "patchvalidation": {
                "evalresult": "false", 
                "evaltcall": "36", 
                "evaltcfailing": "5", 
                "fvalresult": "true", 
                "fvaltcall": "1", 
                "fvaltcfailing": "0", 
                "mvalresult": "false", 
                "mvaltcall": "2106", 
                "mvaltcfailing": "3"
            }, 
            "scope": "LOCAL", 
            "time": "6084", 
            "type": "ReplaceOp", 
            "variant": 3450
        }, 
        {
            "buggyStatement": "x1 = x1 + (0.5 * tolerance)", 
            "generation": 1745, 
            "ingredients": null, 
            "patch": "x1 = x1 + delta", 
            "patchLocation": {
                "className": "org.apache.commons.math.analysis.solvers.BrentSolver", 
                "line": 296, 
                "lineSusp": "0"
            }, 
            "patchvalidation": {
                "evalresult": "false", 
                "evaltcall": "36", 
                "evaltcfailing": "2", 
                "fvalresult": "true", 
                "fvaltcall": "1", 
                "fvaltcfailing": "0", 
                "mvalresult": "false", 
                "mvaltcall": "2106", 
                "mvaltcfailing": "2"
            }, 
            "scope": "LOCAL", 
            "time": "6177", 
            "type": "ReplaceOp", 
            "variant": 3490
        }, 
        {
            "buggyStatement": "absoluteAccuracy = accuracy", 
            "generation": 1746, 
            "ingredients": null, 
            "patch": "remove", 
            "patchLocation": {
                "className": "org.apache.commons.math.ConvergingAlgorithmImpl", 
                "line": 78, 
                "lineSusp": "0"
            }, 
            "patchvalidation": {
                "evalresult": "false", 
                "evaltcall": "18", 
                "evaltcfailing": "3", 
                "fvalresult": "true", 
                "fvaltcall": "1", 
                "fvaltcfailing": "0", 
                "mvalresult": "false", 
                "mvaltcall": "2106", 
                "mvaltcfailing": "10"
            }, 
            "scope": "-", 
            "time": "6253", 
            "type": "RemoveOp", 
            "variant": 3492
        }, 
        {
            "buggyStatement": "delta = 0.5 * dx", 
            "generation": 1751, 
            "ingredients": null, 
            "patch": "p1 = 1.0 - r3", 
            "patchLocation": {
                "className": "org.apache.commons.math.analysis.solvers.BrentSolver", 
                "line": 282, 
                "lineSusp": "0"
            }, 
            "patchvalidation": {
                "evalresult": "false", 
                "evaltcall": "36", 
                "evaltcfailing": "5", 
                "fvalresult": "true", 
                "fvaltcall": "1", 
                "fvaltcfailing": "0", 
                "mvalresult": "false", 
                "mvaltcall": "2106", 
                "mvaltcfailing": "3"
            }, 
            "scope": "LOCAL", 
            "time": "6330", 
            "type": "ReplaceOp", 
            "variant": 3502
        }, 
        {
            "buggyStatement": "t0 = t", 
            "generation": 1766, 
            "ingredients": null, 
            "patch": "nextAction = handler.eventOccurred(t, y, (!((increasing) ^ (forward))))", 
            "patchLocation": {
                "className": "org.apache.commons.math.ode.events.EventState", 
                "line": 285, 
                "lineSusp": "0"
            }, 
            "patchvalidation": {
                "evalresult": "true", 
                "evaltcall": "22", 
                "evaltcfailing": "0", 
                "fvalresult": "true", 
                "fvaltcall": "1", 
                "fvaltcfailing": "0", 
                "mvalresult": "false", 
                "mvaltcall": "2106", 
                "mvaltcfailing": "11"
            }, 
            "scope": "LOCAL", 
            "time": "6416", 
            "type": "ReplaceOp", 
            "variant": 3532
        }, 
        {
            "buggyStatement": "p1 = ((r1 - 1.0) * (r2 - 1.0)) * (r3 - 1.0)", 
            "generation": 1805, 
            "ingredients": null, 
            "patch": "p1 = 1.0 - r3", 
            "patchLocation": {
                "className": "org.apache.commons.math.analysis.solvers.BrentSolver", 
                "line": 270, 
                "lineSusp": "0"
            }, 
            "patchvalidation": {
                "evalresult": "false", 
                "evaltcall": "36", 
                "evaltcfailing": "7", 
                "fvalresult": "true", 
                "fvaltcall": "1", 
                "fvaltcfailing": "0", 
                "mvalresult": "false", 
                "mvaltcall": "2106", 
                "mvaltcfailing": "4"
            }, 
            "scope": "LOCAL", 
            "time": "6532", 
            "type": "InsertAfterOp", 
            "variant": 3610
        }, 
        {
            "buggyStatement": "delta = 0.5 * dx", 
            "generation": 1846, 
            "ingredients": null, 
            "patch": "remove", 
            "patchLocation": {
                "className": "org.apache.commons.math.analysis.solvers.BrentSolver", 
                "line": 282, 
                "lineSusp": "0"
            }, 
            "patchvalidation": {
                "evalresult": "false", 
                "evaltcall": "36", 
                "evaltcfailing": "5", 
                "fvalresult": "true", 
                "fvaltcall": "1", 
                "fvaltcfailing": "0", 
                "mvalresult": "false", 
                "mvaltcall": "2106", 
                "mvaltcfailing": "3"
            }, 
            "scope": "-", 
            "time": "6641", 
            "type": "RemoveOp", 
            "variant": 3692
        }, 
        {
            "buggyStatement": "maximalIterationCount = count", 
            "generation": 1855, 
            "ingredients": null, 
            "patch": "org.apache.commons.math.ConvergingAlgorithmImpl.this.absoluteAccuracy = defaultAbsoluteAccuracy", 
            "patchLocation": {
                "className": "org.apache.commons.math.ConvergingAlgorithmImpl", 
                "line": 93, 
                "lineSusp": "0"
            }, 
            "patchvalidation": {
                "evalresult": "false", 
                "evaltcall": "18", 
                "evaltcfailing": "4", 
                "fvalresult": "true", 
                "fvaltcall": "1", 
                "fvaltcfailing": "0", 
                "mvalresult": "false", 
                "mvaltcall": "2106", 
                "mvaltcfailing": "15"
            }, 
            "scope": "LOCAL", 
            "time": "6723", 
            "type": "ReplaceOp", 
            "variant": 3710
        }, 
        {
            "buggyStatement": "solver.setAbsoluteAccuracy(convergence)", 
            "generation": 1885, 
            "ingredients": null, 
            "patch": "remove", 
            "patchLocation": {
                "className": "org.apache.commons.math.ode.events.EventState", 
                "line": 216, 
                "lineSusp": "0"
            }, 
            "patchvalidation": {
                "evalresult": "true", 
                "evaltcall": "22", 
                "evaltcfailing": "0", 
                "fvalresult": "true", 
                "fvaltcall": "1", 
                "fvaltcfailing": "0", 
                "mvalresult": "false", 
                "mvaltcall": "2106", 
                "mvaltcfailing": "9"
            }, 
            "scope": "-", 
            "time": "6812", 
            "type": "RemoveOp", 
            "variant": 3770
        }, 
        {
            "buggyStatement": "delta = 0.5 * dx", 
            "generation": 1896, 
            "ingredients": null, 
            "patch": "oldDelta = x2 - x1", 
            "patchLocation": {
                "className": "org.apache.commons.math.analysis.solvers.BrentSolver", 
                "line": 282, 
                "lineSusp": "0"
            }, 
            "patchvalidation": {
                "evalresult": "false", 
                "evaltcall": "36", 
                "evaltcfailing": "5", 
                "fvalresult": "true", 
                "fvaltcall": "1", 
                "fvaltcfailing": "0", 
                "mvalresult": "false", 
                "mvaltcall": "2106", 
                "mvaltcfailing": "3"
            }, 
            "scope": "PACKAGE", 
            "time": "6893", 
            "type": "ReplaceOp", 
            "variant": 3792
        }, 
        {
            "buggyStatement": "absoluteAccuracy = accuracy", 
            "generation": 1901, 
            "ingredients": null, 
            "patch": "remove", 
            "patchLocation": {
                "className": "org.apache.commons.math.ConvergingAlgorithmImpl", 
                "line": 78, 
                "lineSusp": "0"
            }, 
            "patchvalidation": {
                "evalresult": "false", 
                "evaltcall": "18", 
                "evaltcfailing": "3", 
                "fvalresult": "true", 
                "fvaltcall": "1", 
                "fvaltcfailing": "0", 
                "mvalresult": "false", 
                "mvaltcall": "2106", 
                "mvaltcfailing": "11"
            }, 
            "scope": "-", 
            "time": "6969", 
            "type": "RemoveOp", 
            "variant": 3802
        }, 
        {
            "buggyStatement": "delta = 0.5 * dx", 
            "generation": 1933, 
            "ingredients": null, 
            "patch": "p = -p", 
            "patchLocation": {
                "className": "org.apache.commons.math.analysis.solvers.BrentSolver", 
                "line": 282, 
                "lineSusp": "0"
            }, 
            "patchvalidation": {
                "evalresult": "false", 
                "evaltcall": "36", 
                "evaltcfailing": "5", 
                "fvalresult": "true", 
                "fvaltcall": "1", 
                "fvaltcfailing": "0", 
                "mvalresult": "false", 
                "mvaltcall": "2106", 
                "mvaltcfailing": "3"
            }, 
            "scope": "LOCAL", 
            "time": "7075", 
            "type": "ReplaceOp", 
            "variant": 3866
        }, 
        {
            "buggyStatement": "delta = 0.5 * dx", 
            "generation": 1973, 
            "ingredients": null, 
            "patch": "remove", 
            "patchLocation": {
                "className": "org.apache.commons.math.analysis.solvers.BrentSolver", 
                "line": 282, 
                "lineSusp": "0"
            }, 
            "patchvalidation": {
                "evalresult": "false", 
                "evaltcall": "36", 
                "evaltcfailing": "5", 
                "fvalresult": "true", 
                "fvaltcall": "1", 
                "fvaltcfailing": "0", 
                "mvalresult": "false", 
                "mvaltcall": "2106", 
                "mvaltcfailing": "3"
            }, 
            "scope": "-", 
            "time": "7173", 
            "type": "RemoveOp", 
            "variant": 3946
        }, 
        {
            "buggyStatement": "solver.setAbsoluteAccuracy(convergence)", 
            "generation": 1979, 
            "ingredients": null, 
            "patch": "remove", 
            "patchLocation": {
                "className": "org.apache.commons.math.ode.events.EventState", 
                "line": 216, 
                "lineSusp": "0"
            }, 
            "patchvalidation": {
                "evalresult": "true", 
                "evaltcall": "22", 
                "evaltcfailing": "0", 
                "fvalresult": "true", 
                "fvaltcall": "1", 
                "fvaltcfailing": "0", 
                "mvalresult": "false", 
                "mvaltcall": "2106", 
                "mvaltcfailing": "9"
            }, 
            "scope": "-", 
            "time": "7249", 
            "type": "RemoveOp", 
            "variant": 3958
        }
    ], 
    "ops": "0", 
    "programVariant": "158", 
    "timeEvaluation": null, 
    "timeTotal": "7290"
}