{
    "date": "Mon Jan 16 03:15:28 CET 2017\n\nremoved classes \n\nzipped \n\ncopied zip \n\n", 
    "gens": "118", 
    "node": "graphene-77.nancy.grid5000.fr", 
    "operations": [
        {
            "buggyStatement": "for (int i = 1 ; i < (f.length) ; i++) {\n\tr += f[i].value(x);\n}", 
            "generation": 4, 
            "ingredients": null, 
            "patch": "remove", 
            "patchLocation": {
                "className": "org.apache.commons.math3.analysis.FunctionUtils", 
                "line": 145, 
                "lineSusp": "0"
            }, 
            "patchvalidation": {
                "evalresult": "true", 
                "evaltcall": "25", 
                "evaltcfailing": "0", 
                "fvalresult": "true", 
                "fvaltcall": "9", 
                "fvaltcfailing": "0", 
                "mvalresult": "false", 
                "mvaltcall": "4030", 
                "mvaltcfailing": "1"
            }, 
            "scope": "-", 
            "time": "1397", 
            "type": "RemoveOp", 
            "variant": 8
        }, 
        {
            "buggyStatement": "fx = ordinate[((-index) - 2)]", 
            "generation": 59, 
            "ingredients": null, 
            "patch": "remove", 
            "patchLocation": {
                "className": "org.apache.commons.math3.analysis.function.StepFunction", 
                "line": 89, 
                "lineSusp": "0"
            }, 
            "patchvalidation": {
                "evalresult": "false", 
                "evaltcall": "11", 
                "evaltcfailing": "2", 
                "fvalresult": "true", 
                "fvaltcall": "9", 
                "fvaltcfailing": "0", 
                "mvalresult": "false", 
                "mvaltcall": "4030", 
                "mvaltcfailing": "3"
            }, 
            "scope": "-", 
            "time": "1780", 
            "type": "RemoveOp", 
            "variant": 118
        }, 
        {
            "buggyStatement": "if (index < (-1)) {\n\tfx = ordinate[((-index) - 2)];\n} else {\n\tif (index >= 0) {\n\t\tfx = ordinate[index];\n\t} else {\n\t\tfx = ordinate[0];\n\t}\n}", 
            "generation": 75, 
            "ingredients": null, 
            "patch": "if (index >= 0) {\n\tfx = ordinate[index];\n} else {\n\tfx = ordinate[0];\n}", 
            "patchLocation": {
                "className": "org.apache.commons.math3.analysis.function.StepFunction", 
                "line": 87, 
                "lineSusp": "0"
            }, 
            "patchvalidation": {
                "evalresult": "false", 
                "evaltcall": "11", 
                "evaltcfailing": "1", 
                "fvalresult": "true", 
                "fvaltcall": "9", 
                "fvaltcfailing": "0", 
                "mvalresult": "false", 
                "mvaltcall": "4030", 
                "mvaltcfailing": "3"
            }, 
            "scope": "LOCAL", 
            "time": "2167", 
            "type": "ReplaceOp", 
            "variant": 150
        }, 
        {
            "buggyStatement": "if (index < (-1)) {\n\tfx = ordinate[((-index) - 2)];\n} else {\n\tif (index >= 0) {\n\t\tfx = ordinate[index];\n\t} else {\n\t\tfx = ordinate[0];\n\t}\n}", 
            "generation": 80, 
            "ingredients": null, 
            "patch": "remove", 
            "patchLocation": {
                "className": "org.apache.commons.math3.analysis.function.StepFunction", 
                "line": 87, 
                "lineSusp": "0"
            }, 
            "patchvalidation": {
                "evalresult": "false", 
                "evaltcall": "11", 
                "evaltcfailing": "4", 
                "fvalresult": "true", 
                "fvaltcall": "9", 
                "fvaltcfailing": "0", 
                "mvalresult": "false", 
                "mvaltcall": "4030", 
                "mvaltcfailing": "3"
            }, 
            "scope": "-", 
            "time": "2355", 
            "type": "RemoveOp", 
            "variant": 160
        }, 
        {
            "buggyStatement": "r += f[i].value(x)", 
            "generation": 89, 
            "ingredients": null, 
            "patch": "remove", 
            "patchLocation": {
                "className": "org.apache.commons.math3.analysis.FunctionUtils", 
                "line": 146, 
                "lineSusp": "0"
            }, 
            "patchvalidation": {
                "evalresult": "true", 
                "evaltcall": "25", 
                "evaltcfailing": "0", 
                "fvalresult": "true", 
                "fvaltcall": "9", 
                "fvaltcfailing": "0", 
                "mvalresult": "false", 
                "mvaltcall": "4030", 
                "mvaltcfailing": "1"
            }, 
            "scope": "-", 
            "time": "2584", 
            "type": "RemoveOp", 
            "variant": 178
        }, 
        {
            "buggyStatement": "if (index < (-1)) {\n\tfx = ordinate[((-index) - 2)];\n} else {\n\tif (index >= 0) {\n\t\tfx = ordinate[index];\n\t} else {\n\t\tfx = ordinate[0];\n\t}\n}", 
            "generation": 96, 
            "ingredients": null, 
            "patch": "remove", 
            "patchLocation": {
                "className": "org.apache.commons.math3.analysis.function.StepFunction", 
                "line": 87, 
                "lineSusp": "0"
            }, 
            "patchvalidation": {
                "evalresult": "false", 
                "evaltcall": "11", 
                "evaltcfailing": "4", 
                "fvalresult": "true", 
                "fvaltcall": "9", 
                "fvaltcfailing": "0", 
                "mvalresult": "false", 
                "mvaltcall": "4030", 
                "mvaltcfailing": "3"
            }, 
            "scope": "-", 
            "time": "2815", 
            "type": "RemoveOp", 
            "variant": 192
        }, 
        {
            "buggyStatement": "fx = ordinate[0]", 
            "generation": 238, 
            "ingredients": null, 
            "patch": "return org.apache.commons.math3.util.FastMath.exp(x)", 
            "patchLocation": {
                "className": "org.apache.commons.math3.analysis.function.StepFunction", 
                "line": 96, 
                "lineSusp": "0"
            }, 
            "patchvalidation": {
                "evalresult": "false", 
                "evaltcall": "11", 
                "evaltcfailing": "1", 
                "fvalresult": "true", 
                "fvaltcall": "9", 
                "fvaltcfailing": "0", 
                "mvalresult": "false", 
                "mvaltcall": "4030", 
                "mvaltcfailing": "3"
            }, 
            "scope": "PACKAGE", 
            "time": "3578", 
            "type": "InsertAfterOp", 
            "variant": 476
        }, 
        {
            "buggyStatement": "fx = ordinate[((-index) - 2)]", 
            "generation": 256, 
            "ingredients": null, 
            "patch": "remove", 
            "patchLocation": {
                "className": "org.apache.commons.math3.analysis.function.StepFunction", 
                "line": 89, 
                "lineSusp": "0"
            }, 
            "patchvalidation": {
                "evalresult": "false", 
                "evaltcall": "11", 
                "evaltcfailing": "2", 
                "fvalresult": "true", 
                "fvaltcall": "9", 
                "fvaltcfailing": "0", 
                "mvalresult": "false", 
                "mvaltcall": "4030", 
                "mvaltcfailing": "3"
            }, 
            "scope": "-", 
            "time": "3808", 
            "type": "RemoveOp", 
            "variant": 512
        }, 
        {
            "buggyStatement": "for (int i = 1 ; i < (f.length) ; i++) {\n\tr += f[i].value(x);\n}", 
            "generation": 304, 
            "ingredients": null, 
            "patch": "remove", 
            "patchLocation": {
                "className": "org.apache.commons.math3.analysis.FunctionUtils", 
                "line": 145, 
                "lineSusp": "0"
            }, 
            "patchvalidation": {
                "evalresult": "true", 
                "evaltcall": "25", 
                "evaltcfailing": "0", 
                "fvalresult": "true", 
                "fvaltcall": "9", 
                "fvaltcfailing": "0", 
                "mvalresult": "false", 
                "mvaltcall": "4030", 
                "mvaltcfailing": "1"
            }, 
            "scope": "-", 
            "time": "4124", 
            "type": "RemoveOp", 
            "variant": 608
        }, 
        {
            "buggyStatement": "if (index < (-1)) {\n\tfx = ordinate[((-index) - 2)];\n} else {\n\tif (index >= 0) {\n\t\tfx = ordinate[index];\n\t} else {\n\t\tfx = ordinate[0];\n\t}\n}", 
            "generation": 358, 
            "ingredients": null, 
            "patch": "remove", 
            "patchLocation": {
                "className": "org.apache.commons.math3.analysis.function.StepFunction", 
                "line": 87, 
                "lineSusp": "0"
            }, 
            "patchvalidation": {
                "evalresult": "false", 
                "evaltcall": "11", 
                "evaltcfailing": "4", 
                "fvalresult": "true", 
                "fvaltcall": "9", 
                "fvaltcfailing": "0", 
                "mvalresult": "false", 
                "mvaltcall": "4030", 
                "mvaltcfailing": "3"
            }, 
            "scope": "-", 
            "time": "4610", 
            "type": "RemoveOp", 
            "variant": 716
        }, 
        {
            "buggyStatement": "if (index < (-1)) {\n\tfx = ordinate[((-index) - 2)];\n} else {\n\tif (index >= 0) {\n\t\tfx = ordinate[index];\n\t} else {\n\t\tfx = ordinate[0];\n\t}\n}", 
            "generation": 386, 
            "ingredients": null, 
            "patch": "remove", 
            "patchLocation": {
                "className": "org.apache.commons.math3.analysis.function.StepFunction", 
                "line": 87, 
                "lineSusp": "0"
            }, 
            "patchvalidation": {
                "evalresult": "false", 
                "evaltcall": "11", 
                "evaltcfailing": "4", 
                "fvalresult": "true", 
                "fvaltcall": "9", 
                "fvaltcfailing": "0", 
                "mvalresult": "false", 
                "mvaltcall": "4030", 
                "mvaltcfailing": "3"
            }, 
            "scope": "-", 
            "time": "4841", 
            "type": "RemoveOp", 
            "variant": 772
        }, 
        {
            "buggyStatement": "r += f[i].value(x)", 
            "generation": 418, 
            "ingredients": null, 
            "patch": "remove", 
            "patchLocation": {
                "className": "org.apache.commons.math3.analysis.FunctionUtils", 
                "line": 146, 
                "lineSusp": "0"
            }, 
            "patchvalidation": {
                "evalresult": "true", 
                "evaltcall": "25", 
                "evaltcfailing": "0", 
                "fvalresult": "true", 
                "fvaltcall": "9", 
                "fvaltcfailing": "0", 
                "mvalresult": "false", 
                "mvaltcall": "4030", 
                "mvaltcfailing": "1"
            }, 
            "scope": "-", 
            "time": "5160", 
            "type": "RemoveOp", 
            "variant": 836
        }, 
        {
            "buggyStatement": "r += f[i].value(x)", 
            "generation": 462, 
            "ingredients": null, 
            "patch": "remove", 
            "patchLocation": {
                "className": "org.apache.commons.math3.analysis.FunctionUtils", 
                "line": 146, 
                "lineSusp": "0"
            }, 
            "patchvalidation": {
                "evalresult": "true", 
                "evaltcall": "25", 
                "evaltcfailing": "0", 
                "fvalresult": "true", 
                "fvaltcall": "9", 
                "fvaltcfailing": "0", 
                "mvalresult": "false", 
                "mvaltcall": "4030", 
                "mvaltcfailing": "1"
            }, 
            "scope": "-", 
            "time": "5604", 
            "type": "RemoveOp", 
            "variant": 924
        }, 
        {
            "buggyStatement": "fx = ordinate[((-index) - 2)]", 
            "generation": 463, 
            "ingredients": null, 
            "patch": "fx = ordinate[0]", 
            "patchLocation": {
                "className": "org.apache.commons.math3.analysis.function.StepFunction", 
                "line": 89, 
                "lineSusp": "0"
            }, 
            "patchvalidation": {
                "evalresult": "false", 
                "evaltcall": "11", 
                "evaltcfailing": "1", 
                "fvalresult": "true", 
                "fvaltcall": "9", 
                "fvaltcfailing": "0", 
                "mvalresult": "false", 
                "mvaltcall": "4030", 
                "mvaltcfailing": "3"
            }, 
            "scope": "LOCAL", 
            "time": "5803", 
            "type": "ReplaceOp", 
            "variant": 926
        }, 
        {
            "buggyStatement": "r += f[i].value(x)", 
            "generation": 486, 
            "ingredients": null, 
            "patch": "remove", 
            "patchLocation": {
                "className": "org.apache.commons.math3.analysis.FunctionUtils", 
                "line": 146, 
                "lineSusp": "0"
            }, 
            "patchvalidation": {
                "evalresult": "true", 
                "evaltcall": "25", 
                "evaltcfailing": "0", 
                "fvalresult": "true", 
                "fvaltcall": "9", 
                "fvaltcfailing": "0", 
                "mvalresult": "false", 
                "mvaltcall": "4030", 
                "mvaltcfailing": "1"
            }, 
            "scope": "-", 
            "time": "6234", 
            "type": "RemoveOp", 
            "variant": 972
        }, 
        {
            "buggyStatement": "r += f[i].value(x)", 
            "generation": 488, 
            "ingredients": null, 
            "patch": "remove", 
            "patchLocation": {
                "className": "org.apache.commons.math3.analysis.FunctionUtils", 
                "line": 146, 
                "lineSusp": "0"
            }, 
            "patchvalidation": {
                "evalresult": "true", 
                "evaltcall": "25", 
                "evaltcfailing": "0", 
                "fvalresult": "true", 
                "fvaltcall": "9", 
                "fvaltcfailing": "0", 
                "mvalresult": "false", 
                "mvaltcall": "4030", 
                "mvaltcfailing": "1"
            }, 
            "scope": "-", 
            "time": "6413", 
            "type": "RemoveOp", 
            "variant": 976
        }, 
        {
            "buggyStatement": "return fx", 
            "generation": 520, 
            "ingredients": null, 
            "patch": "return org.apache.commons.math3.util.FastMath.signum(x)", 
            "patchLocation": {
                "className": "org.apache.commons.math3.analysis.function.StepFunction", 
                "line": 99, 
                "lineSusp": "0"
            }, 
            "patchvalidation": {
                "evalresult": "false", 
                "evaltcall": "11", 
                "evaltcfailing": "4", 
                "fvalresult": "true", 
                "fvaltcall": "9", 
                "fvaltcfailing": "0", 
                "mvalresult": "false", 
                "mvaltcall": "4030", 
                "mvaltcfailing": "3"
            }, 
            "scope": "PACKAGE", 
            "time": "6731", 
            "type": "ReplaceOp", 
            "variant": 1040
        }, 
        {
            "buggyStatement": "for (int i = 1 ; i < (f.length) ; i++) {\n\tr += f[i].value(x);\n}", 
            "generation": 538, 
            "ingredients": null, 
            "patch": "remove", 
            "patchLocation": {
                "className": "org.apache.commons.math3.analysis.FunctionUtils", 
                "line": 145, 
                "lineSusp": "0"
            }, 
            "patchvalidation": {
                "evalresult": "true", 
                "evaltcall": "25", 
                "evaltcfailing": "0", 
                "fvalresult": "true", 
                "fvaltcall": "9", 
                "fvaltcfailing": "0", 
                "mvalresult": "false", 
                "mvaltcall": "4030", 
                "mvaltcfailing": "1"
            }, 
            "scope": "-", 
            "time": "6953", 
            "type": "RemoveOp", 
            "variant": 1076
        }, 
        {
            "buggyStatement": "for (int i = 1 ; i < (f.length) ; i++) {\n\tr += f[i].value(x);\n}", 
            "generation": 546, 
            "ingredients": null, 
            "patch": "remove", 
            "patchLocation": {
                "className": "org.apache.commons.math3.analysis.FunctionUtils", 
                "line": 145, 
                "lineSusp": "0"
            }, 
            "patchvalidation": {
                "evalresult": "true", 
                "evaltcall": "25", 
                "evaltcfailing": "0", 
                "fvalresult": "true", 
                "fvaltcall": "9", 
                "fvaltcfailing": "0", 
                "mvalresult": "false", 
                "mvaltcall": "4030", 
                "mvaltcfailing": "1"
            }, 
            "scope": "-", 
            "time": "7145", 
            "type": "RemoveOp", 
            "variant": 1092
        }, 
        {
            "buggyStatement": "if (index < (-1)) {\n\tfx = ordinate[((-index) - 2)];\n} else {\n\tif (index >= 0) {\n\t\tfx = ordinate[index];\n\t} else {\n\t\tfx = ordinate[0];\n\t}\n}", 
            "generation": 580, 
            "ingredients": null, 
            "patch": "remove", 
            "patchLocation": {
                "className": "org.apache.commons.math3.analysis.function.StepFunction", 
                "line": 87, 
                "lineSusp": "0"
            }, 
            "patchvalidation": {
                "evalresult": "false", 
                "evaltcall": "11", 
                "evaltcfailing": "4", 
                "fvalresult": "true", 
                "fvaltcall": "9", 
                "fvaltcfailing": "0", 
                "mvalresult": "false", 
                "mvaltcall": "4030", 
                "mvaltcfailing": "3"
            }, 
            "scope": "-", 
            "time": "7425", 
            "type": "RemoveOp", 
            "variant": 1160
        }
    ], 
    "ops": "0", 
    "programVariant": "8", 
    "timeEvaluation": null, 
    "timeTotal": "8025"
}