{
    "date": "Sun Jan 29 20:34:53 CET 2017\n\nremoved classes \n\nzipped \n\ncopied zip \n\n", 
    "gens": "55", 
    "node": "graphene-106.nancy.grid5000.fr", 
    "operations": [
        {
            "buggyStatement": "++(count)", 
            "generation": 45, 
            "ingredients": null, 
            "patch": "--(size)", 
            "patchLocation": {
                "className": "org.apache.commons.math.util.OpenIntToDoubleHashMap", 
                "line": 399, 
                "lineSusp": "0"
            }, 
            "patchvalidation": {
                "evalresult": "false", 
                "evaltcall": "40", 
                "evaltcfailing": "3", 
                "fvalresult": "true", 
                "fvaltcall": "9", 
                "fvaltcfailing": "0", 
                "mvalresult": "false", 
                "mvaltcall": "2899", 
                "mvaltcfailing": "4"
            }, 
            "scope": "LOCAL", 
            "time": "908", 
            "type": "ReplaceOp", 
            "variant": 90
        }, 
        {
            "buggyStatement": "++(count)", 
            "generation": 229, 
            "ingredients": null, 
            "patch": "++(size)", 
            "patchLocation": {
                "className": "org.apache.commons.math.util.OpenIntToDoubleHashMap", 
                "line": 399, 
                "lineSusp": "0"
            }, 
            "patchvalidation": {
                "evalresult": "false", 
                "evaltcall": "40", 
                "evaltcfailing": "3", 
                "fvalresult": "true", 
                "fvaltcall": "9", 
                "fvaltcfailing": "0", 
                "mvalresult": "false", 
                "mvaltcall": "2899", 
                "mvaltcfailing": "4"
            }, 
            "scope": "LOCAL", 
            "time": "2664", 
            "type": "ReplaceOp", 
            "variant": 458
        }, 
        {
            "buggyStatement": "entries.remove(index)", 
            "generation": 267, 
            "ingredients": null, 
            "patch": "entries.put(index, value)", 
            "patchLocation": {
                "className": "org.apache.commons.math.linear.OpenMapRealVector", 
                "line": 667, 
                "lineSusp": "0"
            }, 
            "patchvalidation": {
                "evalresult": "false", 
                "evaltcall": "177", 
                "evaltcfailing": "7", 
                "fvalresult": "true", 
                "fvaltcall": "9", 
                "fvaltcfailing": "0", 
                "mvalresult": "true", 
                "mvaltcall": "2899", 
                "mvaltcfailing": "0"
            }, 
            "scope": "LOCAL", 
            "time": "3623", 
            "type": "ReplaceOp", 
            "variant": 534
        }, 
        {
            "buggyStatement": "values[index] = missingEntries", 
            "generation": 282, 
            "ingredients": null, 
            "patch": "int count = 1", 
            "patchLocation": {
                "className": "org.apache.commons.math.util.OpenIntToDoubleHashMap", 
                "line": 397, 
                "lineSusp": "0"
            }, 
            "patchvalidation": {
                "evalresult": "true", 
                "evaltcall": "40", 
                "evaltcfailing": "0", 
                "fvalresult": "true", 
                "fvaltcall": "9", 
                "fvaltcfailing": "0", 
                "mvalresult": "true", 
                "mvaltcall": "2899", 
                "mvaltcfailing": "0"
            }, 
            "scope": "PACKAGE", 
            "time": "3891", 
            "type": "InsertBeforeOp", 
            "variant": 564
        }, 
        {
            "buggyStatement": "keys[index] = 0", 
            "generation": 443, 
            "ingredients": null, 
            "patch": "int count = 1", 
            "patchLocation": {
                "className": "org.apache.commons.math.util.OpenIntToDoubleHashMap", 
                "line": 394, 
                "lineSusp": "0"
            }, 
            "patchvalidation": {
                "evalresult": "true", 
                "evaltcall": "40", 
                "evaltcfailing": "0", 
                "fvalresult": "true", 
                "fvaltcall": "9", 
                "fvaltcfailing": "0", 
                "mvalresult": "true", 
                "mvaltcall": "2899", 
                "mvaltcfailing": "0"
            }, 
            "scope": "PACKAGE", 
            "time": "5315", 
            "type": "InsertBeforeOp", 
            "variant": 886
        }, 
        {
            "buggyStatement": "++(count)", 
            "generation": 594, 
            "ingredients": null, 
            "patch": "remove", 
            "patchLocation": {
                "className": "org.apache.commons.math.util.OpenIntToDoubleHashMap", 
                "line": 399, 
                "lineSusp": "0"
            }, 
            "patchvalidation": {
                "evalresult": "true", 
                "evaltcall": "40", 
                "evaltcfailing": "0", 
                "fvalresult": "true", 
                "fvaltcall": "9", 
                "fvaltcfailing": "0", 
                "mvalresult": "true", 
                "mvaltcall": "2899", 
                "mvaltcfailing": "0"
            }, 
            "scope": "-", 
            "time": "6612", 
            "type": "RemoveOp", 
            "variant": 1188
        }
    ], 
    "ops": "0", 
    "programVariant": "90", 
    "timeEvaluation": null, 
    "timeTotal": "7741"
}