{
    "date": "Sat Jan 28 17:41:46 CET 2017\n\nremoved classes \n\nzipped \n\ncopied zip \n\n", 
    "gens": "399", 
    "node": "graphene-106.nancy.grid5000.fr", 
    "operations": [
        {
            "buggyStatement": "if ((param[2]) <= 0) {\n\tthrow new org.apache.commons.math.exception.NotStrictlyPositiveException(param[2]);\n} ", 
            "generation": 218, 
            "ingredients": null, 
            "patch": "remove", 
            "patchLocation": {
                "className": "org.apache.commons.math.analysis.function.Gaussian", 
                "line": 182, 
                "lineSusp": "0"
            }, 
            "patchvalidation": {
                "evalresult": "false", 
                "evaltcall": "16", 
                "evaltcfailing": "2", 
                "fvalresult": "true", 
                "fvaltcall": "8", 
                "fvaltcfailing": "0", 
                "mvalresult": "false", 
                "mvaltcall": "2299", 
                "mvaltcfailing": "2"
            }, 
            "scope": "-", 
            "time": "2055", 
            "type": "RemoveOp", 
            "variant": 436
        }, 
        {
            "buggyStatement": "for (int j = 0 ; j < (solvedCols) ; ++j) {\n\tint pj = permutation[j];\n\twork1[pj] = ((work3[pj]) * (diag[pj])) / dxNorm;\n}", 
            "generation": 268, 
            "ingredients": null, 
            "patch": "for (int j = 0 ; j < (solvedCols) ; ++j) {\n\tint pj = permutation[j];\n\twork1[pj] *= (diag[pj]) / dxNorm;\n}", 
            "patchLocation": {
                "className": "org.apache.commons.math.optimization.general.LevenbergMarquardtOptimizer", 
                "line": 593, 
                "lineSusp": "0"
            }, 
            "patchvalidation": {
                "evalresult": "true", 
                "evaltcall": "3", 
                "evaltcfailing": "0", 
                "fvalresult": "true", 
                "fvaltcall": "8", 
                "fvaltcfailing": "0", 
                "mvalresult": "false", 
                "mvaltcall": "2299", 
                "mvaltcfailing": "10"
            }, 
            "scope": "LOCAL", 
            "time": "2894", 
            "type": "ReplaceOp", 
            "variant": 536
        }, 
        {
            "buggyStatement": "work1[pj] = ((work3[pj]) * (diag[pj])) / dxNorm", 
            "generation": 354, 
            "ingredients": null, 
            "patch": "determineLMDirection(qy, work1, work2, work3)", 
            "patchLocation": {
                "className": "org.apache.commons.math.optimization.general.LevenbergMarquardtOptimizer", 
                "line": 595, 
                "lineSusp": "0"
            }, 
            "patchvalidation": {
                "evalresult": "true", 
                "evaltcall": "3", 
                "evaltcfailing": "0", 
                "fvalresult": "true", 
                "fvaltcall": "8", 
                "fvaltcfailing": "0", 
                "mvalresult": null, 
                "mvaltcall": null, 
                "mvaltcfailing": null
            }, 
            "scope": "LOCAL", 
            "time": "4650", 
            "type": "InsertBeforeOp", 
            "variant": 708
        }, 
        {
            "buggyStatement": "for (int j = 0 ; j < (solvedCols) ; ++j) {\n\tint pj = permutation[j];\n\twork1[pj] = ((work3[pj]) * (diag[pj])) / dxNorm;\n}", 
            "generation": 363, 
            "ingredients": null, 
            "patch": "for (int j = 0 ; j < (cols) ; ++j) {\n\tdiag[j] = org.apache.commons.math.util.FastMath.max(diag[j], jacNorm[j]);\n}", 
            "patchLocation": {
                "className": "org.apache.commons.math.optimization.general.LevenbergMarquardtOptimizer", 
                "line": 593, 
                "lineSusp": "0"
            }, 
            "patchvalidation": {
                "evalresult": "true", 
                "evaltcall": "3", 
                "evaltcfailing": "0", 
                "fvalresult": "true", 
                "fvaltcall": "8", 
                "fvaltcfailing": "0", 
                "mvalresult": "false", 
                "mvaltcall": "2299", 
                "mvaltcfailing": "9"
            }, 
            "scope": "LOCAL", 
            "time": "4817", 
            "type": "ReplaceOp", 
            "variant": 726
        }, 
        {
            "buggyStatement": "dxNorm = org.apache.commons.math.util.FastMath.sqrt(dxNorm)", 
            "generation": 521, 
            "ingredients": null, 
            "patch": "remove", 
            "patchLocation": {
                "className": "org.apache.commons.math.optimization.general.LevenbergMarquardtOptimizer", 
                "line": 581, 
                "lineSusp": "0"
            }, 
            "patchvalidation": {
                "evalresult": "true", 
                "evaltcall": "3", 
                "evaltcfailing": "0", 
                "fvalresult": "true", 
                "fvaltcall": "8", 
                "fvaltcfailing": "0", 
                "mvalresult": "false", 
                "mvaltcall": "2299", 
                "mvaltcfailing": "11"
            }, 
            "scope": "-", 
            "time": "5584", 
            "type": "RemoveOp", 
            "variant": 1042
        }, 
        {
            "buggyStatement": "if (((lmPar) == 0) || (ratio >= 0.75)) {\n\tdelta = 2 * lmNorm;\n\tlmPar *= 0.5;\n} ", 
            "generation": 543, 
            "ingredients": null, 
            "patch": "if ((cost) != 0) {\n\tfor (int j = 0 ; j < (solvedCols) ; ++j) {\n\t\tint pj = permutation[j];\n\t\tdouble s = jacNorm[pj];\n\t\tif (s != 0) {\n\t\t\tdouble sum = 0;\n\t\t\tfor (int i = 0 ; i <= j ; ++i) {\n\t\t\t\tsum += (weightedResidualJacobian[i][pj]) * (qtf[i]);\n\t\t\t}\n\t\t\tmaxCosine = org.apache.commons.math.util.FastMath.max(maxCosine, ((org.apache.commons.math.util.FastMath.abs(sum)) / (s * (cost))));\n\t\t} \n\t}\n} ", 
            "patchLocation": {
                "className": "org.apache.commons.math.optimization.general.LevenbergMarquardtOptimizer", 
                "line": 391, 
                "lineSusp": "0"
            }, 
            "patchvalidation": {
                "evalresult": "true", 
                "evaltcall": "3", 
                "evaltcfailing": "0", 
                "fvalresult": "true", 
                "fvaltcall": "8", 
                "fvaltcfailing": "0", 
                "mvalresult": "false", 
                "mvaltcall": "2299", 
                "mvaltcfailing": "6"
            }, 
            "scope": "LOCAL", 
            "time": "6269", 
            "type": "ReplaceOp", 
            "variant": 1086
        }, 
        {
            "buggyStatement": "cost = previousCost", 
            "generation": 550, 
            "ingredients": null, 
            "patch": "firstIteration = false", 
            "patchLocation": {
                "className": "org.apache.commons.math.optimization.general.LevenbergMarquardtOptimizer", 
                "line": 417, 
                "lineSusp": "0"
            }, 
            "patchvalidation": {
                "evalresult": "true", 
                "evaltcall": "3", 
                "evaltcfailing": "0", 
                "fvalresult": "true", 
                "fvaltcall": "8", 
                "fvaltcfailing": "0", 
                "mvalresult": "false", 
                "mvaltcall": "2299", 
                "mvaltcfailing": "5"
            }, 
            "scope": "LOCAL", 
            "time": "6437", 
            "type": "ReplaceOp", 
            "variant": 1100
        }, 
        {
            "buggyStatement": "weightedResidualJacobian[i][pk] = temp2", 
            "generation": 630, 
            "ingredients": null, 
            "patch": "cost = java.lang.Double.POSITIVE_INFINITY", 
            "patchLocation": {
                "className": "org.apache.commons.math.optimization.general.LevenbergMarquardtOptimizer", 
                "line": 707, 
                "lineSusp": "0"
            }, 
            "patchvalidation": {
                "evalresult": "true", 
                "evaltcall": "3", 
                "evaltcfailing": "0", 
                "fvalresult": "true", 
                "fvaltcall": "8", 
                "fvaltcfailing": "0", 
                "mvalresult": "false", 
                "mvaltcall": "2299", 
                "mvaltcfailing": "7"
            }, 
            "scope": "PACKAGE", 
            "time": "7040", 
            "type": "ReplaceOp", 
            "variant": 1260
        }, 
        {
            "buggyStatement": "work1[pj] = ((work3[pj]) * (diag[pj])) / dxNorm", 
            "generation": 643, 
            "ingredients": null, 
            "patch": "cost = java.lang.Double.POSITIVE_INFINITY", 
            "patchLocation": {
                "className": "org.apache.commons.math.optimization.general.LevenbergMarquardtOptimizer", 
                "line": 595, 
                "lineSusp": "0"
            }, 
            "patchvalidation": {
                "evalresult": "true", 
                "evaltcall": "3", 
                "evaltcfailing": "0", 
                "fvalresult": "true", 
                "fvaltcall": "8", 
                "fvaltcfailing": "0", 
                "mvalresult": "false", 
                "mvaltcall": "2299", 
                "mvaltcfailing": "8"
            }, 
            "scope": "PACKAGE", 
            "time": "7222", 
            "type": "ReplaceOp", 
            "variant": 1286
        }
    ], 
    "ops": "0", 
    "programVariant": "436", 
    "timeEvaluation": null, 
    "timeTotal": "7511"
}